LICENSE
MANIFEST.in
README
setup.py
attachments/__init__.py
attachments/admin.py
attachments/forms.py
attachments/models.py
attachments/settings.py
attachments/tests.py
attachments/urls.py
attachments/views.py
attachments/management/__init__.py
attachments/management/commands/__init__.py
attachments/management/commands/update_attachments.py
attachments/migrations/0001_initial.py
attachments/migrations/0002_auto__add_field_attachment_suffix__add_field_attachment_is_pic__add_fi.py
attachments/migrations/0003_auto__del_field_attachment_file_size.py
attachments/migrations/__init__.py
django_lb_attachments.egg-info/PKG-INFO
django_lb_attachments.egg-info/SOURCES.txt
django_lb_attachments.egg-info/dependency_links.txt
django_lb_attachments.egg-info/not-zip-safe
django_lb_attachments.egg-info/requires.txt
django_lb_attachments.egg-info/top_level.txt