Metadata-Version: 1.1
Name: django-lb-attachments
Version: 0.8.3
Summary: A django app to manager attachments.
Home-page: https://github.com/vicalloy/django-lb-attachments/
Author: vicalloy
Author-email: zbirder@gmail.com
License: BSD
Keywords: attachment,django
Platform: UNKNOWN
Classifier: Programming Language :: Python
Classifier: Topic :: Software Development :: Libraries :: Python Modules
Classifier: Framework :: Django
Classifier: Environment :: Web Environment
